README.rst
setup.py
ifalg/__init__.py
ifalg/alg_meta.py
ifalg/cli.py
ifalg/hash.py
ifalg/linux.py
ifalg/proc_crypto.py
ifalg/skcipher.py
ifalg/utils.py
ifalg/version.py
ifalg.egg-info/PKG-INFO
ifalg.egg-info/SOURCES.txt
ifalg.egg-info/dependency_links.txt
ifalg.egg-info/requires.txt
ifalg.egg-info/top_level.txt