Metadata-Version: 1.1
Name: ifalg
Version: 0.2
Summary: Library to interface with the Linux kernel crypto API
Home-page: https://github.com/manologab/python-ifalg
Author: Manolo Ramirez T.
Author-email: manologab@gmail.com
License: MIT
Keywords: linux crypto AF_ALG if_alg
Platform: UNKNOWN
Classifier: Development Status :: 3 - Alpha
Classifier: Intended Audience :: Developers
Classifier: Topic :: Security :: Cryptography
Classifier: Topic :: System :: Operating System Kernels :: Linux
Classifier: Operating System :: POSIX :: Linux
Classifier: License :: OSI Approved :: MIT License
Classifier: Programming Language :: Python :: 3
Classifier: Programming Language :: Python :: 3.2
Classifier: Programming Language :: Python :: 3.3
Classifier: Programming Language :: Python :: 3.4
